wattzon/__init__.py
wattzon/common.py
wattzon/link.py
wattzon/snapshot.py
wattzon-0.1.dev1.dist-info/DESCRIPTION.rst
wattzon-0.1.dev1.dist-info/METADATA
wattzon-0.1.dev1.dist-info/RECORD
wattzon-0.1.dev1.dist-info/WHEEL
wattzon-0.1.dev1.dist-info/metadata.json
wattzon-0.1.dev1.dist-info/top_level.txt
