Metadata-Version: 2.0
Name: wattzon
Version: 0.1.dev1
Summary: WattzOn API clients
Home-page: https://github.com/WattzOn/wattzon-python
Author: UNKNOWN
Author-email: UNKNOWN
License: UNKNOWN
Keywords: wattzon link snapshot
Platform: UNKNOWN
Classifier: Development Status :: 3 - Alpha
Classifier: Intended Audience :: Developers
Classifier: Programming Language :: Python :: 3
Requires-Python: >=3
Requires-Dist: requests
